liblog/__init__.py
liblog/liblog.py
liblog-0.0.1.dist-info/LICENSE
liblog-0.0.1.dist-info/METADATA
liblog-0.0.1.dist-info/WHEEL
liblog-0.0.1.dist-info/top_level.txt
liblog-0.0.1.dist-info/RECORD
