Metadata-Version: 2.1
Name: liblog
Version: 0.0.1
Summary: Liblog
Home-page: https://github.com/aztecrabbit/python-liblog
Author: aztecrabbit
Author-email: ars.xda@gmail.com
License: UNKNOWN
Platform: UNKNOWN
Classifier: Programming Language :: Python :: 3
Classifier: License :: OSI Approved :: MIT License
Classifier: Operating System :: OS Independent
Requires-Python: >=3.6
